MVMO/__init__.py
MVMO-1.1.0.dist-info/LICENSE
MVMO-1.1.0.dist-info/METADATA
MVMO-1.1.0.dist-info/WHEEL
MVMO-1.1.0.dist-info/top_level.txt
MVMO-1.1.0.dist-info/RECORD
