Metadata-Version: 2.1
Name: MVMO
Version: 1.1.0
Summary: Python package for heuristic optimization
Home-page: https://github.com/dgusain1/MVMO
Author: Digvijay Gusain
Author-email: d.gusain@tudelft.nl
License: MIT
Platform: UNKNOWN
Classifier: License :: OSI Approved :: MIT License
Classifier: Programming Language :: Python :: 3
Classifier: Programming Language :: Python :: 3.6
Requires-Python: >=3.4
Requires-Dist: numpy
Requires-Dist: pandas
Requires-Dist: tqdm
Requires-Dist: pyDOE
